{"ProjectBreakpoints":"{\"Value\":{},\"CodeBreakpoints\":{}}","OpenedDocuments":"[{\"DocumentPath\":\"Main.xaml\",\"FactoryId\":\"{ACB8E7BA-F093-44C1-9B50-33ECA51AAE16}\"}]","Compiler":"2","ProjectWatches":"{\"Value\":[]}","ProjectActivitiesViewState":"{\"Main.xaml\":[{\"ActivityIdRef\":\"NApplicationCard_1\",\"IsAdvancedOptionsExpanded\":false,\"Categories\":{\"Options\":true,\"Dialog Handling\":true,\"Timings\":true,\"Target application\":true,\"Input/Output\":true},\"Widgets\":{\"OCREngine\":{\"ShowExpanded\":true},\"Body\":{\"ShowExpanded\":true}}},{\"ActivityIdRef\":\"NApplicationCard_2\",\"IsAdvancedOptionsExpanded\":false,\"Categories\":{\"Options\":true,\"Dialog Handling\":true,\"Timings\":true,\"Target application\":true,\"Input/Output\":true},\"Widgets\":{\"OCREngine\":{\"ShowExpanded\":true},\"Body\":{\"ShowExpanded\":true}}},{\"ActivityIdRef\":\"NKeyboardShortcuts_1\",\"IsAdvancedOptionsExpanded\":false,\"Categories\":{\"Timings\":true,\"Options - Offset point\":true,\"Options\":true,\"Input/Output\":true},\"Widgets\":{}},{\"ActivityIdRef\":\"NExtractDataGeneric`1_1\",\"IsAdvancedOptionsExpanded\":false,\"Categories\":{\"Target\":true,\"Timings\":true,\"Input/Output\":true,\"Options\":true,\"Next link - Target\":true},\"Widgets\":{}}]}"}